gee-5.dist-info/DESCRIPTION.rst
gee-5.dist-info/entry_points.txt
gee-5.dist-info/METADATA
gee-5.dist-info/metadata.json
gee-5.dist-info/RECORD
gee-5.dist-info/top_level.txt
gee-5.dist-info/WHEEL
script/__init__.py
script/__init__.pyc
script/gee.py
script/gee.pyc
tests/__init__.py
tests/__init__.pyc
tests/test_unittests.py
tests/__pycache__/test_unittests.cpython-27-PYTEST.pyc
